slides/__init__.py
slides/doi.py
slides/keyvalue_parser.py
slides/page_navigator.py
slides/pdf.py
slides/pdf_generator.py
slides/presentation_viewer.py
slides/semslides.py
slides/slide_browser.py
slides/slide_browser_cmd.py
slides/slide_id.py
slides/slide_viewer.py
slides/slidewalker.py
slides/version.py
slides/resources/KeyValueParser/LG-Utf8-dots.yaml
slides/resources/KeyValueParser/newline-colon-comma.yaml
pysemanticslides-0.3.2.dist-info/METADATA
pysemanticslides-0.3.2.dist-info/WHEEL
pysemanticslides-0.3.2.dist-info/entry_points.txt
pysemanticslides-0.3.2.dist-info/licenses/LICENSE
pysemanticslides-0.3.2.dist-info/RECORD
